mlx_augllm/__init__.py
mlx_augllm/chat_memory.py
mlx_augllm/function_calling.py
mlx_augllm/mlx_augmented_llm.py
mlx_augllm/mlx_llm_interface.py
mlx_augllm/prompt_builder.py
mlx_augllm/test_tools.py
mlx_augllm/toggle_hf_progress_bar.py
mlx_augllm/tool.py
mlx_augllm/tool_handler.py
mlx_augllm-1.3.dist-info/licenses/LICENSE
mlx_augllm-1.3.dist-info/METADATA
mlx_augllm-1.3.dist-info/WHEEL
mlx_augllm-1.3.dist-info/top_level.txt
mlx_augllm-1.3.dist-info/RECORD
