Metadata-Version: 2.4
Name: mlx_augllm
Version: 1.3
Summary: ('A library for augmenting large language models using MLX',)
Home-page: https://github.com/ToPo-ToPo-ToPo/mlx_augllm
Author: Creator name
License: Apache License Version 2.0
Classifier: Programming Language :: Python :: 3
Classifier: License :: OSI Approved :: Apache Software License
Requires-Python: >=3.13.9
License-File: LICENSE
Requires-Dist: mlx-lm
Requires-Dist: mlx_vlm
Requires-Dist: pyyaml
Requires-Dist: Pillow
Dynamic: author
Dynamic: classifier
Dynamic: description
Dynamic: description-content-type
Dynamic: home-page
Dynamic: license
Dynamic: license-file
Dynamic: requires-dist
Dynamic: requires-python
Dynamic: summary
